{
	"name": "DelimitedText1",
	"properties": {
		"linkedServiceName": {
			"referenceName": "AzureBlobStorage1",
			"type": "LinkedServiceReference"
		},
		"annotations": [],
		"type": "DelimitedText",
		"typeProperties": {
			"location": {
				"type": "AzureBlobStorageLocation",
				"folderPath": "edi",
				"container": "adf-staging"
			},
			"columnDelimiter": ";",
			"escapeChar": "\\",
			"firstRowAsHeader": true,
			"quoteChar": "\""
		},
		"schema": [
			{
				"name": "id",
				"type": "String"
			},
			{
				"name": "no",
				"type": "String"
			},
			{
				"name": "postingDate",
				"type": "String"
			},
			{
				"name": "documentDate",
				"type": "String"
			},
			{
				"name": "externalDocumentNo",
				"type": "String"
			},
			{
				"name": "orderNo",
				"type": "String"
			},
			{
				"name": "sellToCustomerNo",
				"type": "String"
			},
			{
				"name": "sellToCustomerName",
				"type": "String"
			},
			{
				"name": "billToCustomerNo",
				"type": "String"
			},
			{
				"name": "shipToCode",
				"type": "String"
			},
			{
				"name": "shipToName",
				"type": "String"
			},
			{
				"name": "shipToAddress",
				"type": "String"
			},
			{
				"name": "shipToAddress2",
				"type": "String"
			},
			{
				"name": "shipToCity",
				"type": "String"
			},
			{
				"name": "shipToPostCode",
				"type": "String"
			},
			{
				"name": "shipToCounty",
				"type": "String"
			},
			{
				"name": "shipToCountryRegionCode",
				"type": "String"
			},
			{
				"name": "shipmentMethodCode",
				"type": "String"
			},
			{
				"name": "packageTrackingNo",
				"type": "String"
			},
			{
				"name": "systemModifiedAt",
				"type": "String"
			}
		]
	},
	"type": "Microsoft.DataFactory/factories/datasets"
}